<DataObject comparison="Ordinal">
  <Section id="">
    <Subsections>
      <Section id="General">
        <Subsections />
        <Entries>
          <Entry key="ElapsedTime">
            <double>119.7262501</double>
          </Entry>
          <Entry key="StartedAt">
            <dateTime>2020-09-10T21:59:50.1315614+05:30</dateTime>
          </Entry>
          <Entry key="EndedAt">
            <dateTime>2020-09-10T22:01:49.8578115+05:30</dateTime>
          </Entry>
          <Entry key="ReplayStatus">
            <LastReplayRunStatus>Passed</LastReplayRunStatus>
          </Entry>
          <Entry key="NumberOfReplayErrors">
            <int>0</int>
          </Entry>
          <Entry key="NumberOfReplayCriticalErrors">
            <int>0</int>
          </Entry>
          <Entry key="NumberOfCompilationErrors">
            <int>0</int>
          </Entry>
        </Entries>
      </Section>
    </Subsections>
    <Entries>
      <Entry key="Iterations">
        <int>5</int>
      </Entry>
    </Entries>
  </Section>
</DataObject>